thumbnailfromzipfile/__init__.py
thumbnailfromzipfile-0.0.2.dist-info/LICENCE.txt
thumbnailfromzipfile-0.0.2.dist-info/METADATA
thumbnailfromzipfile-0.0.2.dist-info/WHEEL
thumbnailfromzipfile-0.0.2.dist-info/top_level.txt
thumbnailfromzipfile-0.0.2.dist-info/RECORD
