Metadata-Version: 2.1
Name: thumbnailfromzipfile
Version: 0.0.2
Summary: Proteus zipcapture File
Author: Proteus Technology PVT. LTD.
Author-email: <apps@baseinformation.com>
Keywords: python,first package
Classifier: Development Status :: 3 - Alpha
Classifier: Intended Audience :: Education
Classifier: Programming Language :: Python :: 2
Classifier: Programming Language :: Python :: 3
Classifier: Operating System :: MacOS :: MacOS X
Classifier: Operating System :: Microsoft :: Windows
License-File: LICENCE.txt
Requires-Dist: flask
Requires-Dist: commonutility
Requires-Dist: imgkit
